simplefetch/__init__.py
pysimplefetch-0.1.1.dist-info/METADATA
pysimplefetch-0.1.1.dist-info/WHEEL
pysimplefetch-0.1.1.dist-info/RECORD
